spl_covid/__init__.py
spl_covid/__main__.py
spl_covid/covidstats.py
spl_covid-0.0.3.dist-info/LICENSE
spl_covid-0.0.3.dist-info/METADATA
spl_covid-0.0.3.dist-info/WHEEL
spl_covid-0.0.3.dist-info/top_level.txt
spl_covid-0.0.3.dist-info/RECORD
