Metadata-Version: 2.1
Name: spl-covid
Version: 0.0.3
Summary: Covid Statistics mini-widget for the amusement of Robert Remez
Home-page: UNKNOWN
Author: Colin Simon-Fellowes
Author-email: colin.tsf@gmail.com
License: UNKNOWN
Platform: UNKNOWN
Classifier: Programming Language :: Python :: 3
Classifier: License :: OSI Approved :: MIT License
Classifier: Operating System :: OS Independent
Requires-Python: >=3.6
License-File: LICENSE
Requires-Dist: tableauscraper
Requires-Dist: xlsxwriter
Requires-Dist: pandas
